ShiyanlouNodejsJiaochengHeji20160904/README.md
ShiyanlouNodejsJiaochengHeji20160904/__init__.py
ShiyanlouNodejsJiaochengHeji20160904/__main__.py
ShiyanlouNodejsJiaochengHeji20160904/file.epub
ShiyanlouNodejsJiaochengHeji20160904/index.html
ShiyanlouNodejsJiaochengHeji20160904/css/__init__.py
ShiyanlouNodejsJiaochengHeji20160904/css/annotations.css
ShiyanlouNodejsJiaochengHeji20160904/css/main.css
ShiyanlouNodejsJiaochengHeji20160904/css/normalize.css
ShiyanlouNodejsJiaochengHeji20160904/css/popup.css
ShiyanlouNodejsJiaochengHeji20160904/font/__init__.py
ShiyanlouNodejsJiaochengHeji20160904/font/fontello.eot
ShiyanlouNodejsJiaochengHeji20160904/font/fontello.svg
ShiyanlouNodejsJiaochengHeji20160904/font/fontello.ttf
ShiyanlouNodejsJiaochengHeji20160904/font/fontello.woff
ShiyanlouNodejsJiaochengHeji20160904/img/__init__.py
ShiyanlouNodejsJiaochengHeji20160904/img/annotator-glyph-sprite.png
ShiyanlouNodejsJiaochengHeji20160904/img/annotator-icon-sprite.png
ShiyanlouNodejsJiaochengHeji20160904/img/apple-touch-icon.png
ShiyanlouNodejsJiaochengHeji20160904/img/cancelfullscreen.png
ShiyanlouNodejsJiaochengHeji20160904/img/close.png
ShiyanlouNodejsJiaochengHeji20160904/img/fullscreen.png
ShiyanlouNodejsJiaochengHeji20160904/img/loader.gif
ShiyanlouNodejsJiaochengHeji20160904/img/menu-icon.png
ShiyanlouNodejsJiaochengHeji20160904/img/save.png
ShiyanlouNodejsJiaochengHeji20160904/img/saved.png
ShiyanlouNodejsJiaochengHeji20160904/img/settings-s.png
ShiyanlouNodejsJiaochengHeji20160904/img/settings.png
ShiyanlouNodejsJiaochengHeji20160904/img/star.png
ShiyanlouNodejsJiaochengHeji20160904/js/__init__.py
ShiyanlouNodejsJiaochengHeji20160904/js/epub.js
ShiyanlouNodejsJiaochengHeji20160904/js/epub.min.js
ShiyanlouNodejsJiaochengHeji20160904/js/epub.min.map
ShiyanlouNodejsJiaochengHeji20160904/js/hooks.min.js
ShiyanlouNodejsJiaochengHeji20160904/js/hooks.min.map
ShiyanlouNodejsJiaochengHeji20160904/js/reader.js
ShiyanlouNodejsJiaochengHeji20160904/js/reader.js.map
shiyanlou_nodejs_jiaocheng_heji_20160904-2024.3.2.0.dist-info/METADATA
shiyanlou_nodejs_jiaocheng_heji_20160904-2024.3.2.0.dist-info/WHEEL
shiyanlou_nodejs_jiaocheng_heji_20160904-2024.3.2.0.dist-info/entry_points.txt
shiyanlou_nodejs_jiaocheng_heji_20160904-2024.3.2.0.dist-info/top_level.txt
shiyanlou_nodejs_jiaocheng_heji_20160904-2024.3.2.0.dist-info/RECORD
